ASTAligner/ASTaligner.py
ASTAligner/__init__.py
ASTAligner-1.0.2.dist-info/METADATA
ASTAligner-1.0.2.dist-info/WHEEL
ASTAligner-1.0.2.dist-info/top_level.txt
ASTAligner-1.0.2.dist-info/RECORD
