Metadata-Version: 2.1
Name: ASTAligner
Version: 1.0.2
Summary: ASTAligner is designed to align tokens from source code snippets to Abstract Syntax Tree (AST) nodes using Tree-sitter for AST generation and various HuggingFace tokenizers for language tokenization. The library supports a wide range of programming languages and Fast tokenizers, enabling precise mapping between source code elements and their AST representations.
Home-page: https://pypi.org/project/ASTAligner/
Author: Semeru Lab
Author-email: svelascodimate@wm.edu
License: MIT License
Classifier: Programming Language :: Python :: 3
Classifier: License :: OSI Approved :: MIT License
Classifier: Operating System :: OS Independent
Requires-Python: >=3.7
Requires-Dist: Flask==3.0.3
Requires-Dist: Flask-Cors==5.0.0
Requires-Dist: protobuf
Requires-Dist: sentencepiece==0.2.0
Requires-Dist: tokenizers==0.20.0
Requires-Dist: transformers==4.45.1
Requires-Dist: tree-sitter==0.23.0
Requires-Dist: tree-sitter-cpp==0.23.1
Requires-Dist: tree-sitter-java==0.23.2
Requires-Dist: tree-sitter-python==0.23.2
Requires-Dist: tree_sitter_c_sharp==0.23.1
Requires-Dist: tree_sitter_go==0.23.3
Requires-Dist: tree_sitter_haskell==0.23.1
Requires-Dist: tree_sitter_javascript==0.23.1
Requires-Dist: tree_sitter_kotlin==1.0.1
Requires-Dist: tree_sitter_rust==0.23.1
Requires-Dist: tree_sitter_html==0.23.2
Requires-Dist: tree_sitter_c==0.23.2
Requires-Dist: tree-sitter-ruby==0.23.1
Requires-Dist: concurrently
